pfedit/__init__.py
pfedit/test.py
pfedit-0.1.1.dist-info/LICENSE
pfedit-0.1.1.dist-info/METADATA
pfedit-0.1.1.dist-info/WHEEL
pfedit-0.1.1.dist-info/top_level.txt
pfedit-0.1.1.dist-info/RECORD
